hftrim/TokenizerTrimmer.py
hftrim/__init__.py
hftrim/ModelTrimmers/BartTrimmer.py
hftrim/ModelTrimmers/BaseTrimmer.py
hftrim/ModelTrimmers/MBartTrimmer.py
hftrim/ModelTrimmers/MT5Trimmer.py
hftrim/ModelTrimmers/T5Trimmer.py
hftrim/ModelTrimmers/__init__.py
hf_trim-3.0.1.dist-info/LICENSE
hf_trim-3.0.1.dist-info/METADATA
hf_trim-3.0.1.dist-info/WHEEL
hf_trim-3.0.1.dist-info/top_level.txt
hf_trim-3.0.1.dist-info/RECORD
