Metadata-Version: 2.1
Name: hf-trim
Version: 3.0.1
Summary: A tool to reduce the size of Hugging Face models via vocabulary trimming.
Home-page: https://github.com/IamAdiSri/hf-trim
Download-URL: https://github.com/IamAdiSri/hf-trim/archive/v3.0.1-beta.tar.gz
Author: Aditya Srivastava
Author-email: adi.srivastava@hotmail.com
License: MPL
Classifier: Development Status :: 4 - Beta
Classifier: Intended Audience :: Science/Research
Classifier: Intended Audience :: Developers
Classifier: License :: OSI Approved :: Mozilla Public License 2.0 (MPL 2.0)
Classifier: Programming Language :: Python :: 3
Classifier: Programming Language :: Python :: 3.8
Classifier: Programming Language :: Python :: 3.9
Classifier: Operating System :: OS Independent
Classifier: Topic :: Scientific/Engineering :: Artificial Intelligence
Requires-Python: >=3.8
License-File: LICENSE
Requires-Dist: numpy (>=1.22.3)
Requires-Dist: protobuf (>=3.19.4)
Requires-Dist: tokenizers (>=0.11.6)
Requires-Dist: torch (>=1.11.0)
Requires-Dist: tqdm (>=4.63.1)
Requires-Dist: transformers (>=4.17.0)
Requires-Dist: sentencepiece (>=0.1.96)
